ya_tagscript/__init__.py
ya_tagscript/py.typed
ya_tagscript/adapters/__init__.py
ya_tagscript/adapters/function_adapter.py
ya_tagscript/adapters/int_adapter.py
ya_tagscript/adapters/object_adapter.py
ya_tagscript/adapters/string_adapter.py
ya_tagscript/adapters/discord_adapters/__init__.py
ya_tagscript/adapters/discord_adapters/attribute_adapter.py
ya_tagscript/adapters/discord_adapters/channel_adapter.py
ya_tagscript/adapters/discord_adapters/guild_adapter.py
ya_tagscript/adapters/discord_adapters/member_adapter.py
ya_tagscript/blocks/__init__.py
ya_tagscript/blocks/actions/__init__.py
ya_tagscript/blocks/actions/command_block.py
ya_tagscript/blocks/actions/delete_block.py
ya_tagscript/blocks/actions/override_block.py
ya_tagscript/blocks/actions/react_block.py
ya_tagscript/blocks/actions/redirect_block.py
ya_tagscript/blocks/actions/silence_block.py
ya_tagscript/blocks/conditional/__init__.py
ya_tagscript/blocks/conditional/all_block.py
ya_tagscript/blocks/conditional/any_block.py
ya_tagscript/blocks/conditional/if_block.py
ya_tagscript/blocks/discord/__init__.py
ya_tagscript/blocks/discord/cooldown_block.py
ya_tagscript/blocks/discord/embed_block.py
ya_tagscript/blocks/flow/__init__.py
ya_tagscript/blocks/flow/break_block.py
ya_tagscript/blocks/flow/shortcutredirect_block.py
ya_tagscript/blocks/flow/stop_block.py
ya_tagscript/blocks/limiters/__init__.py
ya_tagscript/blocks/limiters/blacklist_block.py
ya_tagscript/blocks/limiters/require_block.py
ya_tagscript/blocks/lists/__init__.py
ya_tagscript/blocks/lists/cycle_block.py
ya_tagscript/blocks/lists/list_block.py
ya_tagscript/blocks/math/__init__.py
ya_tagscript/blocks/math/math_block.py
ya_tagscript/blocks/math/ordinal_block.py
ya_tagscript/blocks/meta/__init__.py
ya_tagscript/blocks/meta/comment_block.py
ya_tagscript/blocks/meta/debug_block.py
ya_tagscript/blocks/rng/__init__.py
ya_tagscript/blocks/rng/fiftyfifty_block.py
ya_tagscript/blocks/rng/random_block.py
ya_tagscript/blocks/rng/range_block.py
ya_tagscript-1.6.1.dist-info/METADATA
ya_tagscript-1.6.1.dist-info/WHEEL
ya_tagscript-1.6.1.dist-info/licenses/LICENSE.md
ya_tagscript-1.6.1.dist-info/RECORD
