Metadata-Version: 2.4
Name: ya_tagscript
Version: 1.6.1
Summary: Yet Another TagScript fork. An easy drop in user-provided Templating system.
Project-URL: Changelog, https://ya-tagscript.readthedocs.io/en/latest/changelog.html
Project-URL: Documentation, https://ya-tagscript.readthedocs.io
Project-URL: GitHub, https://github.com/MajorTanya/ya_tagscript
Project-URL: Issues, https://github.com/MajorTanya/ya_tagscript/issues
Author-email: MajorTanya <tanya@majortanya.eu>
License-Expression: CC-BY-4.0
License-File: LICENSE.md
Keywords: tagscript
Classifier: Development Status :: 5 - Production/Stable
Classifier: Intended Audience :: Developers
Classifier: Operating System :: OS Independent
Classifier: Programming Language :: Python :: 3.11
Classifier: Programming Language :: Python :: 3.12
Classifier: Programming Language :: Python :: 3.13
Classifier: Programming Language :: Python :: 3.14
Requires-Python: >=3.11
Requires-Dist: discord-py>=2.5.0
Requires-Dist: pyparsing>=3.2.0
Requires-Dist: python-dateutil>=2.9.0
